{
    "$schema": "https://schema.management.azure.com/schemas/2015-01-01/deploymentTemplate.json#",
    "contentVersion": "1.0.0.0",
    "parameters": {
        "ASPName": {
            "minLength": 1,
            "type": "String"
        },
        "ASPSKU": {
            "defaultValue": "Free",
            "allowedValues": [
                "Free",
                "Shared",
                "Basic",
                "Standard"
            ],
            "type": "String"
        },
        "ASPWorkerSize": {
            "defaultValue": "0",
            "allowedValues": [
                "0",
                "1",
                "2"
            ],
            "type": "String"
        },
        "ASName": {
            "minLength": 1,
            "type": "String"
        },
        "appInsightsName": {
            "minLength": 1,
            "type": "String"
        }
    },
    "resources": [
        {
            "type": "Microsoft.Web/serverfarms",
            "name": "[parameters('ASPName')]",
            "apiVersion": "2014-06-01",
            "location": "[resourceGroup().location]",
            "tags": {
                "displayName": "ASP"
            },
            "properties": {
                "name": "[parameters('ASPName')]",
                "sku": "[parameters('ASPSKU')]",
                "workerSize": "[parameters('ASPWorkerSize')]",
                "numberOfWorkers": 1
            },
            "dependsOn": []
        },
        {
            "type": "Microsoft.Web/sites",
            "name": "[parameters('ASName')]",
            "apiVersion": "2015-08-01",
            "location": "[resourceGroup().location]",
            "tags": {
                "[concat('hidden-related:', resourceGroup().id, '/providers/Microsoft.Web/serverfarms/', parameters('ASPName'))]": "Resource",
                "displayName": "AS"
            },
            "properties": {
                "name": "[parameters('ASName')]",
                "serverFarmId": "[resourceId('Microsoft.Web/serverfarms/', parameters('ASPName'))]",
                "appSettings": [
                    {
                        "name": "APPINSIGHTS_INSTRUMENTATIONKEY",
                        "value": "[reference(concat('microsoft.insights/components/', parameters('appInsightsName'))).InstrumentationKey]"
                    }
                ]
            },
            "dependsOn": [
                "[concat('Microsoft.Web/serverfarms/', parameters('ASPName'))]",
                "[resourceId('microsoft.insights/components/', parameters('appInsightsName'))]"
            ]
        },
        {
            "type": "Microsoft.Insights/components",
            "name": "[parameters('appInsightsName')]",
            "apiVersion": "2014-04-01",
            "location": "West Europe",
            "tags": {
                "[concat('hidden-link:', resourceGroup().id, '/providers/Microsoft.Web/sites/', parameters('ASName'))]": "Resource",
                "displayName": "AppInsightsComponent"
            },
            "properties": {
                "applicationId": "[parameters('appInsightsName')]"
            }
        }
    ],
    "outputs": {}
}
